evolvo/__init__.py
evolvo/code_generator.py
evolvo/core.py
evolvo/utils.py
evolvo-0.1.1.dist-info/licenses/LICENSE
examples/__init__.py
examples/basic_usage.py
examples/code_generation.py
evolvo-0.1.1.dist-info/METADATA
evolvo-0.1.1.dist-info/WHEEL
evolvo-0.1.1.dist-info/top_level.txt
evolvo-0.1.1.dist-info/RECORD
